manage_wrapper/__init__.py
manage_wrapper/django_manage.py
monitoring/__init__.py
monitoring/constants.py
monitoring/metrics.py
news/__init__.py
news/apps.py
news/constants.py
news/functions.py
news/models.py
news/validators.py
news/admin/__init__.py
news/admin/actions.py
news/admin/filters.py
news/admin/forms.py
news/handlers/__init__.py
news/handlers/commands.py
news/handlers/dispatcher.py
news/handlers/messages.py
news/management/__init__.py
news/management/commands/__init__.py
news/management/commands/delete_links.py
news/management/commands/drop_db.py
news/management/commands/load_sources.py
news/management/commands/run_polling.py
news/migrations/0001_initial.py
news/migrations/0002_auto_20230524_1324.py
news/migrations/0003_auto_20230529_1043.py
news/migrations/0004_stream_is_enabled.py
news/migrations/0005_reaction.py
news/migrations/0006_auto_20240626_1526.py
news/migrations/0007_adminmessage.py
news/migrations/0008_auto_20240627_1515.py
news/migrations/__init__.py
news_bot/__init__.py
news_bot/settings.py
news_bot/urls.py
news_bot/views.py
news_bot/wsgi.py
news_parsing/__init__.py
news_parsing/admin.py
news_parsing/apps.py
news_parsing/feeds.py
news_parsing/items.py
news_parsing/middlewares.py
news_parsing/models.py
news_parsing/pipelines.py
news_parsing/settings.py
news_parsing/validators.py
news_parsing/migrations/0001_initial.py
news_parsing/migrations/__init__.py
news_parsing/spiders/__init__.py
news_parsing/spiders/constants.py
news_parsing/spiders/handlers.py
news_parsing/spiders/mailru.py
news_vk_bot-0.1.16.dist-info/LICENSE
news_vk_bot-0.1.16.dist-info/METADATA
news_vk_bot-0.1.16.dist-info/WHEEL
news_vk_bot-0.1.16.dist-info/entry_points.txt
news_vk_bot-0.1.16.dist-info/top_level.txt
news_vk_bot-0.1.16.dist-info/RECORD
